agent_upd/__init__.py
agent_upd-0.1.1.dist-info/METADATA
agent_upd-0.1.1.dist-info/WHEEL
agent_upd-0.1.1.dist-info/entry_points.txt
agent_upd-0.1.1.dist-info/RECORD
