Metadata-Version: 2.4
Name: agent-upd
Version: 0.1.1
Summary: Update Claude Code sub-agents from GitHub to your project
License-Expression: MIT
Requires-Python: >=3.10
Requires-Dist: agent-skills-upd>=0.1.1
